MANIFEST.in
README
README.rst
setup.py
src/django_uwsgi_admin2.egg-info/PKG-INFO
src/django_uwsgi_admin2.egg-info/SOURCES.txt
src/django_uwsgi_admin2.egg-info/dependency_links.txt
src/django_uwsgi_admin2.egg-info/not-zip-safe
src/django_uwsgi_admin2.egg-info/requires.txt
src/django_uwsgi_admin2.egg-info/top_level.txt
src/uwsgi_admin/__init__.py
src/uwsgi_admin/admin.py
src/uwsgi_admin/panels.py
src/uwsgi_admin/views.py
src/uwsgi_admin/templates/uwsgi_admin/uwsgi.html
src/uwsgi_admin/templates/uwsgi_admin/uwsgi_panel.html