Metadata-Version: 1.1
Name: django-uwsgi-admin2
Version: 0.2.0
Summary: uWSGI monitoring page in django admin and debug_toolbar panel.
Home-page: https://github.com/ionelmc/django-uwsgi-admin
Author: Ionel Cristian Mărieș
Author-email: contact@ionelmc.ro
License: BSD
Platform: UNKNOWN
Classifier: Development Status :: 4 - Beta
Classifier: Framework :: Django
Classifier: Intended Audience :: Developers
Classifier: License :: OSI Approved :: BSD License
Classifier: Operating System :: OS Independent
Classifier: Programming Language :: Python
Classifier: Topic :: Internet :: WWW/HTTP
